{
    "fluentMethods": true,
    "clientRootFolder": "",
    "relationships": [],
    "fields": [
        {
            "fieldName": "firstName",
            "fieldType": "String",
            "fieldValidateRules": [
                "required",
                "minlength",
                "pattern"
            ],
            "fieldValidateRulesMinlength": "1",
            "fieldValidateRulesPattern": "[a-zA-Z]{2,}"
        },
        {
            "fieldName": "lastName",
            "fieldType": "String",
            "fieldValidateRules": [
                "required",
                "pattern"
            ],
            "fieldValidateRulesPattern": "[a-zA-Z]{2,}"
        },
        {
            "fieldName": "topSkill",
            "fieldType": "String"
        }
    ],
    "changelogDate": "20190216100838",
    "dto": "no",
    "searchEngine": false,
    "service": "serviceClass",
    "entityTableName": "developer",
    "databaseType": "sql",
    "jpaMetamodelFiltering": false,
    "pagination": "pagination"
}
